zcc/__init__.py
zcc/__main__.py
zcc/constants.py
zcc/controller.py
zcc/description.py
zcc/device.py
zcc/discovery.py
zcc/errors.py
zcc/manufacture_info.py
zcc/protocol.py
zcc/socket.py
zcc/trace.py
zcc/watchdog.py
zcc_helper-3.7.dist-info/licenses/LICENSE.txt
zcc_helper-3.7.dist-info/METADATA
zcc_helper-3.7.dist-info/WHEEL
zcc_helper-3.7.dist-info/top_level.txt
zcc_helper-3.7.dist-info/RECORD
