Metadata-Version: 2.4
Name: zcc_helper
Version: 3.7
Summary: ZIMI ZCC helper module
Author: Mark Hannon
Author-email: mark.hannon@gmail.com
License: MIT
Project-URL: Changelog, https://bitbucket.org/mark_hannon/zcc/src/master/CHANGELOG.md
Project-URL: Source, https://bitbucket.org/mark_hannon/zcc
Classifier: Programming Language :: Python :: 3.12
License-File: LICENSE.txt
Dynamic: author
Dynamic: author-email
Dynamic: classifier
Dynamic: description
Dynamic: description-content-type
Dynamic: license
Dynamic: license-file
Dynamic: project-url
Dynamic: summary
